{
  "description": "USN-3976-1 fixed a vulnerability in Samba. The update introduced a\nregression causing Samba to occasionally crash. This update fixes the\nproblem.\n\nWe apologize for the inconvenience.\n\nOriginal advisory details:\n\n Isaac Boukris and Andrew Bartlett discovered that Samba incorrectly checked\n S4U2Self packets. In certain environments, a remote attacker could possibly\n use this issue to escalate privileges.\n",
  "releases": {
    "bionic": {
      "allbinaries": {
        "libparse-pidl-perl": {
          "pocket": "security",
          "version": "2:4.7.6+dfsg~ubuntu-0ubuntu2.11"
        },
        "samba": {
          "pocket": "security",
          "version": "2:4.7.6+dfsg~ubuntu-0ubuntu2.11"
        },
        "libnss-winbind": {
          "pocket": "security",
          "version": "2:4.7.6+dfsg~ubuntu-0ubuntu2.11"
        },
        "libpam-winbind": {
          "pocket": "security",
          "version": "2:4.7.6+dfsg~ubuntu-0ubuntu2.11"
        },
        "libsmbclient": {
          "pocket": "security",
          "version": "2:4.7.6+dfsg~ubuntu-0ubuntu2.11"
        },
        "smbclient": {
          "pocket": "security",
          "version": "2:4.7.6+dfsg~ubuntu-0ubuntu2.11"
        },
        "samba-vfs-modules": {
          "pocket": "security",
          "version": "2:4.7.6+dfsg~ubuntu-0ubuntu2.11"
        },
        "libwbclient0": {
          "pocket": "security",
          "version": "2:4.7.6+dfsg~ubuntu-0ubuntu2.11"
        },
        "samba-testsuite": {
          "pocket": "security",
          "version": "2:4.7.6+dfsg~ubuntu-0ubuntu2.11"
        },
        "samba-common-bin": {
          "pocket": "security",
          "version": "2:4.7.6+dfsg~ubuntu-0ubuntu2.11"
        },
        "winbind": {
          "pocket": "security",
          "version": "2:4.7.6+dfsg~ubuntu-0ubuntu2.11"
        },
        "libwbclient-dev": {
          "pocket": "security",
          "version": "2:4.7.6+dfsg~ubuntu-0ubuntu2.11"
        },
        "samba-dsdb-modules": {
          "pocket": "security",
          "version": "2:4.7.6+dfsg~ubuntu-0ubuntu2.11"
        },
        "samba-dev": {
          "pocket": "security",
          "version": "2:4.7.6+dfsg~ubuntu-0ubuntu2.11"
        },
        "libsmbclient-dev": {
          "pocket": "security",
          "version": "2:4.7.6+dfsg~ubuntu-0ubuntu2.11"
        },
        "python-samba": {
          "pocket": "security",
          "version": "2:4.7.6+dfsg~ubuntu-0ubuntu2.11"
        },
        "samba-common": {
          "pocket": "security",
          "version": "2:4.7.6+dfsg~ubuntu-0ubuntu2.11"
        },
        "ctdb": {
          "pocket": "security",
          "version": "2:4.7.6+dfsg~ubuntu-0ubuntu2.11"
        },
        "samba-libs": {
          "pocket": "security",
          "version": "2:4.7.6+dfsg~ubuntu-0ubuntu2.11"
        },
        "registry-tools": {
          "pocket": "security",
          "version": "2:4.7.6+dfsg~ubuntu-0ubuntu2.11"
        }
      },
      "binaries": {
        "samba": {
          "pocket": "security",
          "version": "2:4.7.6+dfsg~ubuntu-0ubuntu2.11"
        }
      },
      "archs": {
        "all": {
          "urls": {
            "http://security.ubuntu.com/ubuntu/pool/main/s/samba/samba-common_4.7.6+dfsg~ubuntu-0ubuntu2.11_all.deb": {
              "md5": "66a801715ae091f4317a7eb942353b4d",
              "size": 71324
            }
          }
        },
        "amd64": {
          "urls": {
            "http://security.ubuntu.com/ubuntu/pool/main/s/samba/libparse-pidl-perl_4.7.6+dfsg~ubuntu-0ubuntu2.11_amd64.deb": {
              "md5": "9c6f77dab6ccce44ffe0fb0ee8db07fc",
              "size": 100020
            },
            "http://security.ubuntu.com/ubuntu/pool/main/s/samba/libwbclient0_4.7.6+dfsg~ubuntu-0ubuntu2.11_amd64.deb": {
              "md5": "4f9c6309857ac18efaa4e15c19667a79",
              "size": 33100
            },
            "http://security.ubuntu.com/ubuntu/pool/main/s/samba/libnss-winbind_4.7.6+dfsg~ubuntu-0ubuntu2.11_amd64.deb": {
              "md5": "7a01309f2515f5e988460e7ea29d8eda",
              "size": 10604
            },
            "http://security.ubuntu.com/ubuntu/pool/main/s/samba/samba-dsdb-modules_4.7.6+dfsg~ubuntu-0ubuntu2.11_amd64.deb": {
              "md5": "9ba326b73bfc17d968e3120fcaf7a5e2",
              "size": 245088
            },
            "http://security.ubuntu.com/ubuntu/pool/universe/s/samba/registry-tools_4.7.6+dfsg~ubuntu-0ubuntu2.11_amd64.deb": {
              "md5": "31e7023d0ec7431f6836446fcb6335be",
              "size": 29220
            },
            "http://security.ubuntu.com/ubuntu/pool/main/s/samba/samba-vfs-modules_4.7.6+dfsg~ubuntu-0ubuntu2.11_amd64.deb": {
              "md5": "48d6a0f7194ff791c3d4d6c7e48cfb00",
              "size": 297076
            },
            "http://security.ubuntu.com/ubuntu/pool/main/s/samba/python-samba_4.7.6+dfsg~ubuntu-0ubuntu2.11_amd64.deb": {
              "md5": "4f49bbe2e12b0bf5e83759c9e2ab1f14",
              "size": 1922904
            },
            "http://security.ubuntu.com/ubuntu/pool/universe/s/samba/ctdb_4.7.6+dfsg~ubuntu-0ubuntu2.11_amd64.deb": {
              "md5": "0e692d49c3c05a4aa9ad1d3ce32ea265",
              "size": 587144
            },
            "http://security.ubuntu.com/ubuntu/pool/main/s/samba/libsmbclient_4.7.6+dfsg~ubuntu-0ubuntu2.11_amd64.deb": {
              "md5": "981d5f9b68efe2e0713c3c907d20092d",
              "size": 54412
            },
            "http://security.ubuntu.com/ubuntu/pool/main/s/samba/libpam-winbind_4.7.6+dfsg~ubuntu-0ubuntu2.11_amd64.deb": {
              "md5": "cd48b94164b7bc51716fb2c6b30fe1a1",
              "size": 28692
            },
            "http://security.ubuntu.com/ubuntu/pool/main/s/samba/libsmbclient-dev_4.7.6+dfsg~ubuntu-0ubuntu2.11_amd64.deb": {
              "md5": "bd8c539d24d32d935eddb80ec6253801",
              "size": 41056
            },
            "http://security.ubuntu.com/ubuntu/pool/main/s/samba/samba-dev_4.7.6+dfsg~ubuntu-0ubuntu2.11_amd64.deb": {
              "md5": "6224ae88997de1dea5febef38274d122",
              "size": 229888
            },
            "http://security.ubuntu.com/ubuntu/pool/universe/s/samba/samba-testsuite_4.7.6+dfsg~ubuntu-0ubuntu2.11_amd64.deb": {
              "md5": "b738cf4862156859c5818539596761ec",
              "size": 1734112
            },
            "http://security.ubuntu.com/ubuntu/pool/main/s/samba/samba-common-bin_4.7.6+dfsg~ubuntu-0ubuntu2.11_amd64.deb": {
              "md5": "ccc735390a9ddf550c362c97826b07f8",
              "size": 520012
            },
            "http://security.ubuntu.com/ubuntu/pool/main/s/samba/samba_4.7.6+dfsg~ubuntu-0ubuntu2.11_amd64.deb": {
              "md5": "3bae5bd6fc1cce1556760c065077119e",
              "size": 854700
            },
            "http://security.ubuntu.com/ubuntu/pool/main/s/samba/smbclient_4.7.6+dfsg~ubuntu-0ubuntu2.11_amd64.deb": {
              "md5": "da21c7c19cbd4425e4e3525856ead65d",
              "size": 351508
            },
            "http://security.ubuntu.com/ubuntu/pool/main/s/samba/winbind_4.7.6+dfsg~ubuntu-0ubuntu2.11_amd64.deb": {
              "md5": "633502721534ee72cefeb8dd5b7a4bee",
              "size": 443948
            },
            "http://security.ubuntu.com/ubuntu/pool/main/s/samba/samba-libs_4.7.6+dfsg~ubuntu-0ubuntu2.11_amd64.deb": {
              "md5": "a10c48309451c9b3e64edb3da8e91745",
              "size": 5249000
            },
            "http://security.ubuntu.com/ubuntu/pool/main/s/samba/libwbclient-dev_4.7.6+dfsg~ubuntu-0ubuntu2.11_amd64.deb": {
              "md5": "5bda7f5b5e9537751b7beb9e5f0f5480",
              "size": 12504
            }
          }
        },
        "ppc64el": {
          "urls": {
            "http://ports.ubuntu.com/pool/main/s/samba/libwbclient-dev_4.7.6+dfsg~ubuntu-0ubuntu2.11_ppc64el.deb": {
              "md5": "16dafb9cc72d7e07ff5f7cf92f44641e",
              "size": 12504
            },
            "http://ports.ubuntu.com/pool/main/s/samba/python-samba_4.7.6+dfsg~ubuntu-0ubuntu2.11_ppc64el.deb": {
              "md5": "0f97dded19fe83e284dc2fea1a8035b7",
              "size": 1646272
            },
            "http://ports.ubuntu.com/pool/universe/s/samba/samba-testsuite_4.7.6+dfsg~ubuntu-0ubuntu2.11_ppc64el.deb": {
              "md5": "70e73d57d1831c7dc05545b51b9408c8",
              "size": 1695736
            },
            "http://ports.ubuntu.com/pool/main/s/samba/libnss-winbind_4.7.6+dfsg~ubuntu-0ubuntu2.11_ppc64el.deb": {
              "md5": "0e9d78e93510b1d5694e1bf8bedee13a",
              "size": 10692
            },
            "http://ports.ubuntu.com/pool/main/s/samba/samba-libs_4.7.6+dfsg~ubuntu-0ubuntu2.11_ppc64el.deb": {
              "md5": "b2c7917d53b2eea9442cdb425e7c8d03",
              "size": 5024524
            },
            "http://ports.ubuntu.com/pool/main/s/samba/libsmbclient_4.7.6+dfsg~ubuntu-0ubuntu2.11_ppc64el.deb": {
              "md5": "54a95a706d5eb18c39ef5b815e3ce0d3",
              "size": 54288
            },
            "http://ports.ubuntu.com/pool/universe/s/samba/registry-tools_4.7.6+dfsg~ubuntu-0ubuntu2.11_ppc64el.deb": {
              "md5": "f41ae15283567033318736898d1de177",
              "size": 29280
            },
            "http://ports.ubuntu.com/pool/universe/s/samba/ctdb_4.7.6+dfsg~ubuntu-0ubuntu2.11_ppc64el.deb": {
              "md5": "2b18b315730324647765e80514615f99",
              "size": 546804
            },
            "http://ports.ubuntu.com/pool/main/s/samba/samba-common-bin_4.7.6+dfsg~ubuntu-0ubuntu2.11_ppc64el.deb": {
              "md5": "bd132737931e4e08ab5550f9318bef1a",
              "size": 516796
            },
            "http://ports.ubuntu.com/pool/main/s/samba/samba-dev_4.7.6+dfsg~ubuntu-0ubuntu2.11_ppc64el.deb": {
              "md5": "0f21f05694ca97751aab1c3eae7ea2b8",
              "size": 229904
            },
            "http://ports.ubuntu.com/pool/main/s/samba/libparse-pidl-perl_4.7.6+dfsg~ubuntu-0ubuntu2.11_ppc64el.deb": {
              "md5": "279dca256731075ac0900397598ea6f3",
              "size": 100028
            },
            "http://ports.ubuntu.com/pool/main/s/samba/libwbclient0_4.7.6+dfsg~ubuntu-0ubuntu2.11_ppc64el.deb": {
              "md5": "979b6ca705791ef3c762ded9d5b81346",
              "size": 33924
            },
            "http://ports.ubuntu.com/pool/main/s/samba/samba-dsdb-modules_4.7.6+dfsg~ubuntu-0ubuntu2.11_ppc64el.deb": {
              "md5": "795c163448b28d31334bf1657654b21c",
              "size": 248444
            },
            "http://ports.ubuntu.com/pool/main/s/samba/smbclient_4.7.6+dfsg~ubuntu-0ubuntu2.11_ppc64el.deb": {
              "md5": "7b629206b4ef9c15cc01971afe27a3cc",
              "size": 339592
            },
            "http://ports.ubuntu.com/pool/main/s/samba/samba_4.7.6+dfsg~ubuntu-0ubuntu2.11_ppc64el.deb": {
              "md5": "ab8bc28e47021f7fb90b0884c4dc5a9f",
              "size": 846680
            },
            "http://ports.ubuntu.com/pool/main/s/samba/winbind_4.7.6+dfsg~ubuntu-0ubuntu2.11_ppc64el.deb": {
              "md5": "e12e5f29c945ce35641936031a475eed",
              "size": 433612
            },
            "http://ports.ubuntu.com/pool/main/s/samba/samba-vfs-modules_4.7.6+dfsg~ubuntu-0ubuntu2.11_ppc64el.deb": {
              "md5": "a9f7cf11e6f4993537826ea22afeb01b",
              "size": 310712
            },
            "http://ports.ubuntu.com/pool/main/s/samba/libpam-winbind_4.7.6+dfsg~ubuntu-0ubuntu2.11_ppc64el.deb": {
              "md5": "a83cdca3fdda3b59db432acca0336896",
              "size": 29060
            },
            "http://ports.ubuntu.com/pool/main/s/samba/libsmbclient-dev_4.7.6+dfsg~ubuntu-0ubuntu2.11_ppc64el.deb": {
              "md5": "f5d7f70dae17a3309a3d7d0e6386b1c2",
              "size": 41068
            }
          }
        },
        "s390x": {
          "urls": {
            "http://ports.ubuntu.com/pool/main/s/samba/libparse-pidl-perl_4.7.6+dfsg~ubuntu-0ubuntu2.11_s390x.deb": {
              "md5": "e82440457179b7b3700f7c80ae666ab3",
              "size": 100024
            },
            "http://ports.ubuntu.com/pool/main/s/samba/libnss-winbind_4.7.6+dfsg~ubuntu-0ubuntu2.11_s390x.deb": {
              "md5": "57244fbce035ddd8f1103a27d3da1b78",
              "size": 10172
            },
            "http://ports.ubuntu.com/pool/main/s/samba/libpam-winbind_4.7.6+dfsg~ubuntu-0ubuntu2.11_s390x.deb": {
              "md5": "9fe3d0c520bb20b17f8287b87c710b06",
              "size": 26832
            },
            "http://ports.ubuntu.com/pool/main/s/samba/libsmbclient_4.7.6+dfsg~ubuntu-0ubuntu2.11_s390x.deb": {
              "md5": "815025508d8b68a586a220b7090931f7",
              "size": 49640
            },
            "http://ports.ubuntu.com/pool/main/s/samba/libsmbclient-dev_4.7.6+dfsg~ubuntu-0ubuntu2.11_s390x.deb": {
              "md5": "198608d5e83735cc49ccbed49463636d",
              "size": 41052
            },
            "http://ports.ubuntu.com/pool/main/s/samba/samba-dsdb-modules_4.7.6+dfsg~ubuntu-0ubuntu2.11_s390x.deb": {
              "md5": "d7227a80aed77d8dd1f44c8475a9831f",
              "size": 223916
            },
            "http://ports.ubuntu.com/pool/main/s/samba/samba_4.7.6+dfsg~ubuntu-0ubuntu2.11_s390x.deb": {
              "md5": "b510337966406adafe132c857981333d",
              "size": 805288
            },
            "http://ports.ubuntu.com/pool/main/s/samba/python-samba_4.7.6+dfsg~ubuntu-0ubuntu2.11_s390x.deb": {
              "md5": "519e51e352b9684070ef0d6743a37fd3",
              "size": 1843760
            },
            "http://ports.ubuntu.com/pool/main/s/samba/samba-vfs-modules_4.7.6+dfsg~ubuntu-0ubuntu2.11_s390x.deb": {
              "md5": "e7e8ce9b9e973b3382b8c8a38d550249",
              "size": 277532
            },
            "http://ports.ubuntu.com/pool/main/s/samba/samba-libs_4.7.6+dfsg~ubuntu-0ubuntu2.11_s390x.deb": {
              "md5": "9ff173b78713d30fd8afdd5acab416ec",
              "size": 4781272
            },
            "http://ports.ubuntu.com/pool/universe/s/samba/samba-testsuite_4.7.6+dfsg~ubuntu-0ubuntu2.11_s390x.deb": {
              "md5": "0f486b01d718bfe5b9fb2506b1c22980",
              "size": 1549308
            },
            "http://ports.ubuntu.com/pool/main/s/samba/libwbclient-dev_4.7.6+dfsg~ubuntu-0ubuntu2.11_s390x.deb": {
              "md5": "6ccdba3e3ca36fab02ceb109ef36c58a",
              "size": 12496
            },
            "http://ports.ubuntu.com/pool/main/s/samba/samba-dev_4.7.6+dfsg~ubuntu-0ubuntu2.11_s390x.deb": {
              "md5": "8538d25746a2c7a9740f4222c3a8f2c6",
              "size": 229880
            },
            "http://ports.ubuntu.com/pool/main/s/samba/samba-common-bin_4.7.6+dfsg~ubuntu-0ubuntu2.11_s390x.deb": {
              "md5": "ec5d6e82df42f4da36a3cb03cae4c57d",
              "size": 493668
            },
            "http://ports.ubuntu.com/pool/universe/s/samba/ctdb_4.7.6+dfsg~ubuntu-0ubuntu2.11_s390x.deb": {
              "md5": "00578813a0c411255d9b0f8b1be5a696",
              "size": 544304
            },
            "http://ports.ubuntu.com/pool/main/s/samba/winbind_4.7.6+dfsg~ubuntu-0ubuntu2.11_s390x.deb": {
              "md5": "2a621af28bacfe98f710c1ac03154eea",
              "size": 409656
            },
            "http://ports.ubuntu.com/pool/main/s/samba/libwbclient0_4.7.6+dfsg~ubuntu-0ubuntu2.11_s390x.deb": {
              "md5": "6c178f872f3d710da775b9d01dfb9595",
              "size": 31220
            },
            "http://ports.ubuntu.com/pool/universe/s/samba/registry-tools_4.7.6+dfsg~ubuntu-0ubuntu2.11_s390x.deb": {
              "md5": "929cb31255a1a94eaeb2e9f1a357de85",
              "size": 28672
            },
            "http://ports.ubuntu.com/pool/main/s/samba/smbclient_4.7.6+dfsg~ubuntu-0ubuntu2.11_s390x.deb": {
              "md5": "946bf6d8a5e6defb53b9bcce84410a81",
              "size": 334532
            }
          }
        },
        "source": {
          "urls": {
            "http://security.ubuntu.com/ubuntu/pool/main/s/samba/samba_4.7.6+dfsg~ubuntu-0ubuntu2.11.debian.tar.xz": {
              "md5": "af9324f5982c1827df04dc251c75474a",
              "size": 268900
            },
            "http://security.ubuntu.com/ubuntu/pool/main/s/samba/samba_4.7.6+dfsg~ubuntu.orig.tar.gz": {
              "md5": "e02a2fb8c22971df80016bf71d74ff9c",
              "size": 16838870
            },
            "http://security.ubuntu.com/ubuntu/pool/main/s/samba/samba_4.7.6+dfsg~ubuntu-0ubuntu2.11.dsc": {
              "md5": "e398405b3413a01ef4b5b6a8f0602719",
              "size": 4294
            }
          }
        },
        "i386": {
          "urls": {
            "http://security.ubuntu.com/ubuntu/pool/main/s/samba/libsmbclient-dev_4.7.6+dfsg~ubuntu-0ubuntu2.11_i386.deb": {
              "md5": "324fff0747491cc13b3dd97cce482a0c",
              "size": 41048
            },
            "http://security.ubuntu.com/ubuntu/pool/main/s/samba/libsmbclient_4.7.6+dfsg~ubuntu-0ubuntu2.11_i386.deb": {
              "md5": "7755c3d0f0e37d589cba2685ea6df45a",
              "size": 58704
            },
            "http://security.ubuntu.com/ubuntu/pool/universe/s/samba/registry-tools_4.7.6+dfsg~ubuntu-0ubuntu2.11_i386.deb": {
              "md5": "a467dac4e93d468b29457fbcf710261f",
              "size": 29284
            },
            "http://security.ubuntu.com/ubuntu/pool/main/s/samba/libnss-winbind_4.7.6+dfsg~ubuntu-0ubuntu2.11_i386.deb": {
              "md5": "d666a70201f7c93c1e5c54fedab46829",
              "size": 10916
            },
            "http://security.ubuntu.com/ubuntu/pool/universe/s/samba/samba-testsuite_4.7.6+dfsg~ubuntu-0ubuntu2.11_i386.deb": {
              "md5": "ea012ca50ccb96675828b65430c21209",
              "size": 1862940
            },
            "http://security.ubuntu.com/ubuntu/pool/main/s/samba/samba-vfs-modules_4.7.6+dfsg~ubuntu-0ubuntu2.11_i386.deb": {
              "md5": "19743032e1a6cb30f31c72d009214546",
              "size": 312332
            },
            "http://security.ubuntu.com/ubuntu/pool/main/s/samba/libparse-pidl-perl_4.7.6+dfsg~ubuntu-0ubuntu2.11_i386.deb": {
              "md5": "8100a8586178c1dee79dcfc46406c1e8",
              "size": 100024
            },
            "http://security.ubuntu.com/ubuntu/pool/main/s/samba/samba-common-bin_4.7.6+dfsg~ubuntu-0ubuntu2.11_i386.deb": {
              "md5": "d523dd7a2a06438fcdc874007c7e1656",
              "size": 555912
            },
            "http://security.ubuntu.com/ubuntu/pool/main/s/samba/libpam-winbind_4.7.6+dfsg~ubuntu-0ubuntu2.11_i386.deb": {
              "md5": "224d791a8963608d5603026bf3e3d272",
              "size": 30452
            },
            "http://security.ubuntu.com/ubuntu/pool/main/s/samba/libwbclient0_4.7.6+dfsg~ubuntu-0ubuntu2.11_i386.deb": {
              "md5": "ca57ad50c2e9ceb408551e7fe55e67f1",
              "size": 35668
            },
            "http://security.ubuntu.com/ubuntu/pool/main/s/samba/libwbclient-dev_4.7.6+dfsg~ubuntu-0ubuntu2.11_i386.deb": {
              "md5": "51af06cc81b325422bc0e5369513da43",
              "size": 12492
            },
            "http://security.ubuntu.com/ubuntu/pool/universe/s/samba/ctdb_4.7.6+dfsg~ubuntu-0ubuntu2.11_i386.deb": {
              "md5": "9329210f2a484363ac4ecd185fad1119",
              "size": 623948
            },
            "http://security.ubuntu.com/ubuntu/pool/main/s/samba/samba_4.7.6+dfsg~ubuntu-0ubuntu2.11_i386.deb": {
              "md5": "c1e3fc17e9bf877478e0b361844c6c8f",
              "size": 893880
            },
            "http://security.ubuntu.com/ubuntu/pool/main/s/samba/winbind_4.7.6+dfsg~ubuntu-0ubuntu2.11_i386.deb": {
              "md5": "ab7728c0aede822701b3e4029645a330",
              "size": 483888
            },
            "http://security.ubuntu.com/ubuntu/pool/main/s/samba/samba-libs_4.7.6+dfsg~ubuntu-0ubuntu2.11_i386.deb": {
              "md5": "7fc4a4acd9762982811de493329939a4",
              "size": 5616540
            },
            "http://security.ubuntu.com/ubuntu/pool/main/s/samba/samba-dsdb-modules_4.7.6+dfsg~ubuntu-0ubuntu2.11_i386.deb": {
              "md5": "245dfc6921efdbc8e956d3712d05cda2",
              "size": 265440
            },
            "http://security.ubuntu.com/ubuntu/pool/main/s/samba/samba-dev_4.7.6+dfsg~ubuntu-0ubuntu2.11_i386.deb": {
              "md5": "8eaeefac5acd5f0e67b14852a5c20463",
              "size": 229876
            },
            "http://security.ubuntu.com/ubuntu/pool/main/s/samba/python-samba_4.7.6+dfsg~ubuntu-0ubuntu2.11_i386.deb": {
              "md5": "5609c95ce233c2aa5babae11843b81b7",
              "size": 1743980
            },
            "http://security.ubuntu.com/ubuntu/pool/main/s/samba/smbclient_4.7.6+dfsg~ubuntu-0ubuntu2.11_i386.deb": {
              "md5": "57160d0a3129ab4dd0a83b9f6a0be056",
              "size": 379480
            }
          }
        },
        "armhf": {
          "urls": {
            "http://ports.ubuntu.com/pool/main/s/samba/samba-libs_4.7.6+dfsg~ubuntu-0ubuntu2.11_armhf.deb": {
              "md5": "64276ac078c8366cc010030ee1544c12",
              "size": 4485488
            },
            "http://ports.ubuntu.com/pool/main/s/samba/smbclient_4.7.6+dfsg~ubuntu-0ubuntu2.11_armhf.deb": {
              "md5": "72a056d95fac4f208ea1286d9f9390e4",
              "size": 308604
            },
            "http://ports.ubuntu.com/pool/main/s/samba/libwbclient0_4.7.6+dfsg~ubuntu-0ubuntu2.11_armhf.deb": {
              "md5": "329deb895c2ecddc7c19e98eef97db61",
              "size": 29296
            },
            "http://ports.ubuntu.com/pool/main/s/samba/python-samba_4.7.6+dfsg~ubuntu-0ubuntu2.11_armhf.deb": {
              "md5": "10fee41bef8f680f556ad49e2bf3b643",
              "size": 1541612
            },
            "http://ports.ubuntu.com/pool/main/s/samba/libnss-winbind_4.7.6+dfsg~ubuntu-0ubuntu2.11_armhf.deb": {
              "md5": "8986c606ac1c94de9fca791907a2b85e",
              "size": 9712
            },
            "http://ports.ubuntu.com/pool/main/s/samba/samba-dev_4.7.6+dfsg~ubuntu-0ubuntu2.11_armhf.deb": {
              "md5": "df3715b65e62d208c98a8c740aff53ac",
              "size": 229868
            },
            "http://ports.ubuntu.com/pool/universe/s/samba/samba-testsuite_4.7.6+dfsg~ubuntu-0ubuntu2.11_armhf.deb": {
              "md5": "0bdbc5e200baf76696ad7794bff0be19",
              "size": 1724180
            },
            "http://ports.ubuntu.com/pool/main/s/samba/samba_4.7.6+dfsg~ubuntu-0ubuntu2.11_armhf.deb": {
              "md5": "e107efdbb9314f13f7724cf6438aec8c",
              "size": 796944
            },
            "http://ports.ubuntu.com/pool/main/s/samba/libpam-winbind_4.7.6+dfsg~ubuntu-0ubuntu2.11_armhf.deb": {
              "md5": "b00785b68593db69f1d07dc6f7113cc6",
              "size": 25296
            },
            "http://ports.ubuntu.com/pool/main/s/samba/libparse-pidl-perl_4.7.6+dfsg~ubuntu-0ubuntu2.11_armhf.deb": {
              "md5": "cd8915bbb1bcb5f693cff1c7ba3a48e9",
              "size": 100020
            },
            "http://ports.ubuntu.com/pool/main/s/samba/libsmbclient-dev_4.7.6+dfsg~ubuntu-0ubuntu2.11_armhf.deb": {
              "md5": "51a06f6952dc364f90357b315ee699c9",
              "size": 41060
            },
            "http://ports.ubuntu.com/pool/main/s/samba/samba-dsdb-modules_4.7.6+dfsg~ubuntu-0ubuntu2.11_armhf.deb": {
              "md5": "61a4e30daa7ad3c9ceaa4c355826b637",
              "size": 217664
            },
            "http://ports.ubuntu.com/pool/main/s/samba/samba-vfs-modules_4.7.6+dfsg~ubuntu-0ubuntu2.11_armhf.deb": {
              "md5": "e94f49d82a92e3b46c37057495b66776",
              "size": 266408
            },
            "http://ports.ubuntu.com/pool/main/s/samba/libwbclient-dev_4.7.6+dfsg~ubuntu-0ubuntu2.11_armhf.deb": {
              "md5": "f549d30ab5dc632005ff05733bebbaeb",
              "size": 12500
            },
            "http://ports.ubuntu.com/pool/universe/s/samba/ctdb_4.7.6+dfsg~ubuntu-0ubuntu2.11_armhf.deb": {
              "md5": "c9bad9198d6935216a259a5d7af53234",
              "size": 508048
            },
            "http://ports.ubuntu.com/pool/main/s/samba/winbind_4.7.6+dfsg~ubuntu-0ubuntu2.11_armhf.deb": {
              "md5": "a666c25d91ab023aafe8e48f8b1e41c8",
              "size": 392988
            },
            "http://ports.ubuntu.com/pool/universe/s/samba/registry-tools_4.7.6+dfsg~ubuntu-0ubuntu2.11_armhf.deb": {
              "md5": "7cf18abead115f9f16952390dfbb11d6",
              "size": 25852
            },
            "http://ports.ubuntu.com/pool/main/s/samba/libsmbclient_4.7.6+dfsg~ubuntu-0ubuntu2.11_armhf.deb": {
              "md5": "f8bc803a7a499cb6bc967b77da5bb3d8",
              "size": 47704
            },
            "http://ports.ubuntu.com/pool/main/s/samba/samba-common-bin_4.7.6+dfsg~ubuntu-0ubuntu2.11_armhf.deb": {
              "md5": "c4570579fd7a33a7eaaf85122320292e",
              "size": 475464
            }
          }
        },
        "arm64": {
          "urls": {
            "http://ports.ubuntu.com/pool/main/s/samba/libparse-pidl-perl_4.7.6+dfsg~ubuntu-0ubuntu2.11_arm64.deb": {
              "md5": "a6e554978458409131daa33cca3468f5",
              "size": 100020
            },
            "http://ports.ubuntu.com/pool/main/s/samba/samba-common-bin_4.7.6+dfsg~ubuntu-0ubuntu2.11_arm64.deb": {
              "md5": "5ac286ebbe1d031822a4cd2b7f2fa01a",
              "size": 466752
            },
            "http://ports.ubuntu.com/pool/main/s/samba/libwbclient0_4.7.6+dfsg~ubuntu-0ubuntu2.11_arm64.deb": {
              "md5": "65492cc251f96fff9dcdd10d2881acc2",
              "size": 30008
            },
            "http://ports.ubuntu.com/pool/main/s/samba/samba-dev_4.7.6+dfsg~ubuntu-0ubuntu2.11_arm64.deb": {
              "md5": "52352e47c3dd4a9f36e6452ea8fc199d",
              "size": 229884
            },
            "http://ports.ubuntu.com/pool/main/s/samba/smbclient_4.7.6+dfsg~ubuntu-0ubuntu2.11_arm64.deb": {
              "md5": "0ac98c3c66813215c294d20829a73f76",
              "size": 307948
            },
            "http://ports.ubuntu.com/pool/main/s/samba/libwbclient-dev_4.7.6+dfsg~ubuntu-0ubuntu2.11_arm64.deb": {
              "md5": "2d2298ccc834701061cf457d157d2604",
              "size": 12492
            },
            "http://ports.ubuntu.com/pool/main/s/samba/samba-vfs-modules_4.7.6+dfsg~ubuntu-0ubuntu2.11_arm64.deb": {
              "md5": "d1b0b3a6476fe485e9a13b33b3ce034e",
              "size": 257920
            },
            "http://ports.ubuntu.com/pool/main/s/samba/samba_4.7.6+dfsg~ubuntu-0ubuntu2.11_arm64.deb": {
              "md5": "f14d603bbfae807e6f9842c62d0ec9aa",
              "size": 778544
            },
            "http://ports.ubuntu.com/pool/main/s/samba/python-samba_4.7.6+dfsg~ubuntu-0ubuntu2.11_arm64.deb": {
              "md5": "66cededc3c7f62997dbb0ae0f4ba4a6d",
              "size": 1535520
            },
            "http://ports.ubuntu.com/pool/main/s/samba/winbind_4.7.6+dfsg~ubuntu-0ubuntu2.11_arm64.deb": {
              "md5": "bb33b9616916ffd044607920d302f39d",
              "size": 383348
            },
            "http://ports.ubuntu.com/pool/main/s/samba/samba-libs_4.7.6+dfsg~ubuntu-0ubuntu2.11_arm64.deb": {
              "md5": "88273730581b5e9305412c286a72f1a4",
              "size": 4387688
            },
            "http://ports.ubuntu.com/pool/main/s/samba/samba-dsdb-modules_4.7.6+dfsg~ubuntu-0ubuntu2.11_arm64.deb": {
              "md5": "049e3a6d52d00240c27b6717eceffc8c",
              "size": 209240
            },
            "http://ports.ubuntu.com/pool/universe/s/samba/registry-tools_4.7.6+dfsg~ubuntu-0ubuntu2.11_arm64.deb": {
              "md5": "617ee47213b22d90b5089f5a6f797b97",
              "size": 26808
            },
            "http://ports.ubuntu.com/pool/main/s/samba/libsmbclient-dev_4.7.6+dfsg~ubuntu-0ubuntu2.11_arm64.deb": {
              "md5": "f04a3d707526a75528798463887a8dc0",
              "size": 41056
            },
            "http://ports.ubuntu.com/pool/universe/s/samba/ctdb_4.7.6+dfsg~ubuntu-0ubuntu2.11_arm64.deb": {
              "md5": "f5db31c27461affe731dde6c78aeb0cd",
              "size": 497860
            },
            "http://ports.ubuntu.com/pool/universe/s/samba/samba-testsuite_4.7.6+dfsg~ubuntu-0ubuntu2.11_arm64.deb": {
              "md5": "92860ad09ea4ac78a2436f85fd4e5d7c",
              "size": 1471072
            },
            "http://ports.ubuntu.com/pool/main/s/samba/libnss-winbind_4.7.6+dfsg~ubuntu-0ubuntu2.11_arm64.deb": {
              "md5": "f21f3998210af87c0a30176c998095cc",
              "size": 9732
            },
            "http://ports.ubuntu.com/pool/main/s/samba/libsmbclient_4.7.6+dfsg~ubuntu-0ubuntu2.11_arm64.deb": {
              "md5": "4771c9402eb4b36ff9c3d30fe85ea64c",
              "size": 45608
            },
            "http://ports.ubuntu.com/pool/main/s/samba/libpam-winbind_4.7.6+dfsg~ubuntu-0ubuntu2.11_arm64.deb": {
              "md5": "e3090b12bd9d7f767ead1f7fb7e94a64",
              "size": 26120
            }
          }
        }
      },
      "sources": {
        "samba": {
          "version": "2:4.7.6+dfsg~ubuntu-0ubuntu2.11",
          "description": "SMB/CIFS file, print, and login server for Unix"
        }
      }
    },
    "xenial": {
      "allbinaries": {
        "libparse-pidl-perl": {
          "pocket": "security",
          "version": "2:4.3.11+dfsg-0ubuntu0.16.04.21"
        },
        "samba": {
          "pocket": "security",
          "version": "2:4.3.11+dfsg-0ubuntu0.16.04.21"
        },
        "libnss-winbind": {
          "pocket": "security",
          "version": "2:4.3.11+dfsg-0ubuntu0.16.04.21"
        },
        "libpam-winbind": {
          "pocket": "security",
          "version": "2:4.3.11+dfsg-0ubuntu0.16.04.21"
        },
        "libsmbclient": {
          "pocket": "security",
          "version": "2:4.3.11+dfsg-0ubuntu0.16.04.21"
        },
        "smbclient": {
          "pocket": "security",
          "version": "2:4.3.11+dfsg-0ubuntu0.16.04.21"
        },
        "samba-vfs-modules": {
          "pocket": "security",
          "version": "2:4.3.11+dfsg-0ubuntu0.16.04.21"
        },
        "libwbclient0": {
          "pocket": "security",
          "version": "2:4.3.11+dfsg-0ubuntu0.16.04.21"
        },
        "samba-testsuite": {
          "pocket": "security",
          "version": "2:4.3.11+dfsg-0ubuntu0.16.04.21"
        },
        "samba-common-bin": {
          "pocket": "security",
          "version": "2:4.3.11+dfsg-0ubuntu0.16.04.21"
        },
        "winbind": {
          "pocket": "security",
          "version": "2:4.3.11+dfsg-0ubuntu0.16.04.21"
        },
        "libwbclient-dev": {
          "pocket": "security",
          "version": "2:4.3.11+dfsg-0ubuntu0.16.04.21"
        },
        "samba-dsdb-modules": {
          "pocket": "security",
          "version": "2:4.3.11+dfsg-0ubuntu0.16.04.21"
        },
        "samba-dev": {
          "pocket": "security",
          "version": "2:4.3.11+dfsg-0ubuntu0.16.04.21"
        },
        "libsmbclient-dev": {
          "pocket": "security",
          "version": "2:4.3.11+dfsg-0ubuntu0.16.04.21"
        },
        "python-samba": {
          "pocket": "security",
          "version": "2:4.3.11+dfsg-0ubuntu0.16.04.21"
        },
        "samba-common": {
          "pocket": "security",
          "version": "2:4.3.11+dfsg-0ubuntu0.16.04.21"
        },
        "ctdb": {
          "pocket": "security",
          "version": "2:4.3.11+dfsg-0ubuntu0.16.04.21"
        },
        "samba-libs": {
          "pocket": "security",
          "version": "2:4.3.11+dfsg-0ubuntu0.16.04.21"
        },
        "registry-tools": {
          "pocket": "security",
          "version": "2:4.3.11+dfsg-0ubuntu0.16.04.21"
        }
      },
      "binaries": {
        "samba": {
          "pocket": "security",
          "version": "2:4.3.11+dfsg-0ubuntu0.16.04.21"
        }
      },
      "archs": {
        "all": {
          "urls": {
            "http://security.ubuntu.com/ubuntu/pool/main/s/samba/samba-common_4.3.11+dfsg-0ubuntu0.16.04.21_all.deb": {
              "md5": "808a14795df6cadcad3498f34eeb935d",
              "size": 83900
            }
          }
        },
        "amd64": {
          "urls": {
            "http://security.ubuntu.com/ubuntu/pool/main/s/samba/samba-dev_4.3.11+dfsg-0ubuntu0.16.04.21_amd64.deb": {
              "md5": "70c3a07c4d83cd502b1fb31dd4cba640",
              "size": 279910
            },
            "http://security.ubuntu.com/ubuntu/pool/main/s/samba/smbclient_4.3.11+dfsg-0ubuntu0.16.04.21_amd64.deb": {
              "md5": "b853979bae849744216cd2f5c6caa291",
              "size": 310424
            },
            "http://security.ubuntu.com/ubuntu/pool/main/s/samba/samba_4.3.11+dfsg-0ubuntu0.16.04.21_amd64.deb": {
              "md5": "c997853d8d624860ac4c698f3fd2018b",
              "size": 901664
            },
            "http://security.ubuntu.com/ubuntu/pool/main/s/samba/winbind_4.3.11+dfsg-0ubuntu0.16.04.21_amd64.deb": {
              "md5": "5bac0d718a9d1aaccaca13cd8f90fa9b",
              "size": 410614
            },
            "http://security.ubuntu.com/ubuntu/pool/main/s/samba/python-samba_4.3.11+dfsg-0ubuntu0.16.04.21_amd64.deb": {
              "md5": "15cc6d28f6297ea9cb5a17c97f9e3016",
              "size": 1056844
            },
            "http://security.ubuntu.com/ubuntu/pool/main/s/samba/samba-common-bin_4.3.11+dfsg-0ubuntu0.16.04.21_amd64.deb": {
              "md5": "a4654bdef13d6bb90bff0a151a887b17",
              "size": 506496
            },
            "http://security.ubuntu.com/ubuntu/pool/main/s/samba/libwbclient0_4.3.11+dfsg-0ubuntu0.16.04.21_amd64.deb": {
              "md5": "8db04a9dadf9fe048e2e197d1820d280",
              "size": 30316
            },
            "http://security.ubuntu.com/ubuntu/pool/main/s/samba/samba-dbg_4.3.11+dfsg-0ubuntu0.16.04.21_amd64.deb": {
              "md5": "394804e34c0fa0f7814e983b002f3b7f",
              "size": 34033770
            },
            "http://security.ubuntu.com/ubuntu/pool/universe/s/samba/ctdb_4.3.11+dfsg-0ubuntu0.16.04.21_amd64.deb": {
              "md5": "0317fa2de771cce0b8077d88d44cc3c7",
              "size": 428220
            },
            "http://security.ubuntu.com/ubuntu/pool/universe/s/samba/libpam-winbind_4.3.11+dfsg-0ubuntu0.16.04.21_amd64.deb": {
              "md5": "741f8db1b8ae97e71a67bbb24497bba6",
              "size": 28302
            },
            "http://security.ubuntu.com/ubuntu/pool/main/s/samba/samba-dsdb-modules_4.3.11+dfsg-0ubuntu0.16.04.21_amd64.deb": {
              "md5": "f9fdd4cea3a9e47d528fff57f0876a25",
              "size": 215550
            },
            "http://security.ubuntu.com/ubuntu/pool/main/s/samba/libparse-pidl-perl_4.3.11+dfsg-0ubuntu0.16.04.21_amd64.deb": {
              "md5": "7d0d325a49aca31a75935ba7103b9ff0",
              "size": 95348
            },
            "http://security.ubuntu.com/ubuntu/pool/universe/s/samba/registry-tools_4.3.11+dfsg-0ubuntu0.16.04.21_amd64.deb": {
              "md5": "2d088d434eb1d2c133cb2ccf4cdd0feb",
              "size": 27946
            },
            "http://security.ubuntu.com/ubuntu/pool/main/s/samba/libwbclient-dev_4.3.11+dfsg-0ubuntu0.16.04.21_amd64.deb": {
              "md5": "1de675841507b8482268766baf4d6914",
              "size": 12270
            },
            "http://security.ubuntu.com/ubuntu/pool/universe/s/samba/libnss-winbind_4.3.11+dfsg-0ubuntu0.16.04.21_amd64.deb": {
              "md5": "73b07e30b3d024a614997a9c7426cb75",
              "size": 12288
            },
            "http://security.ubuntu.com/ubuntu/pool/main/s/samba/libsmbclient_4.3.11+dfsg-0ubuntu0.16.04.21_amd64.deb": {
              "md5": "a3c303522fe52ce3e9f62144d5d2db0d",
              "size": 53204
            },
            "http://security.ubuntu.com/ubuntu/pool/main/s/samba/libsmbclient-dev_4.3.11+dfsg-0ubuntu0.16.04.21_amd64.deb": {
              "md5": "2b8a26460bf22398580a3466deee2944",
              "size": 40846
            },
            "http://security.ubuntu.com/ubuntu/pool/main/s/samba/samba-vfs-modules_4.3.11+dfsg-0ubuntu0.16.04.21_amd64.deb": {
              "md5": "e81556dc6850de3ae4055af0d9ab9a31",
              "size": 256482
            },
            "http://security.ubuntu.com/ubuntu/pool/universe/s/samba/samba-testsuite_4.3.11+dfsg-0ubuntu0.16.04.21_amd64.deb": {
              "md5": "bee8f509fee3d7f9aa43a1040f299a35",
              "size": 1632098
            },
            "http://security.ubuntu.com/ubuntu/pool/main/s/samba/samba-libs_4.3.11+dfsg-0ubuntu0.16.04.21_amd64.deb": {
              "md5": "c729273f519f69011ba9b114d95c98a5",
              "size": 5170480
            }
          }
        },
        "ppc64el": {
          "urls": {
            "http://ports.ubuntu.com/pool/main/s/samba/winbind_4.3.11+dfsg-0ubuntu0.16.04.21_ppc64el.deb": {
              "md5": "b70a88cc9d23c03c599fbdd758b742c5",
              "size": 383074
            },
            "http://ports.ubuntu.com/pool/main/s/samba/samba-libs_4.3.11+dfsg-0ubuntu0.16.04.21_ppc64el.deb": {
              "md5": "950b7691ba496dfb5eb072d500dca01b",
              "size": 4666328
            },
            "http://ports.ubuntu.com/pool/main/s/samba/libparse-pidl-perl_4.3.11+dfsg-0ubuntu0.16.04.21_ppc64el.deb": {
              "md5": "18454be1109eb67854f327f77ed55c6c",
              "size": 95580
            },
            "http://ports.ubuntu.com/pool/universe/s/samba/registry-tools_4.3.11+dfsg-0ubuntu0.16.04.21_ppc64el.deb": {
              "md5": "767364bf000d42d3698034f3219f9773",
              "size": 28704
            },
            "http://ports.ubuntu.com/pool/main/s/samba/samba-common-bin_4.3.11+dfsg-0ubuntu0.16.04.21_ppc64el.deb": {
              "md5": "3eb95837f67106aad1006d7b0a6b7786",
              "size": 483728
            },
            "http://ports.ubuntu.com/pool/main/s/samba/libsmbclient-dev_4.3.11+dfsg-0ubuntu0.16.04.21_ppc64el.deb": {
              "md5": "62f6579acde9d3ebcaf06fbee2e15313",
              "size": 40728
            },
            "http://ports.ubuntu.com/pool/main/s/samba/python-samba_4.3.11+dfsg-0ubuntu0.16.04.21_ppc64el.deb": {
              "md5": "1af1b408aa06eed635350bb09a3be5a8",
              "size": 901026
            },
            "http://ports.ubuntu.com/pool/main/s/samba/libwbclient-dev_4.3.11+dfsg-0ubuntu0.16.04.21_ppc64el.deb": {
              "md5": "5c34d8c8cf0f67d1f106db3340bf5a89",
              "size": 12334
            },
            "http://ports.ubuntu.com/pool/main/s/samba/samba-dsdb-modules_4.3.11+dfsg-0ubuntu0.16.04.21_ppc64el.deb": {
              "md5": "1c943451e69dbcc4bbec1ae1f56c935a",
              "size": 209020
            },
            "http://ports.ubuntu.com/pool/main/s/samba/samba-dev_4.3.11+dfsg-0ubuntu0.16.04.21_ppc64el.deb": {
              "md5": "d08e36837091361f15abbe362c7a8519",
              "size": 279852
            },
            "http://ports.ubuntu.com/pool/main/s/samba/samba-dbg_4.3.11+dfsg-0ubuntu0.16.04.21_ppc64el.deb": {
              "md5": "040ca3002759cac0459bd16c1df9f012",
              "size": 36093980
            },
            "http://ports.ubuntu.com/pool/main/s/samba/smbclient_4.3.11+dfsg-0ubuntu0.16.04.21_ppc64el.deb": {
              "md5": "ea8b65adb82dc1eb1364b8cc24836a2e",
              "size": 292270
            },
            "http://ports.ubuntu.com/pool/main/s/samba/samba_4.3.11+dfsg-0ubuntu0.16.04.21_ppc64el.deb": {
              "md5": "7eb17272d4b2a45a1d6daf9009c272aa",
              "size": 869114
            },
            "http://ports.ubuntu.com/pool/main/s/samba/samba-vfs-modules_4.3.11+dfsg-0ubuntu0.16.04.21_ppc64el.deb": {
              "md5": "9234ee443c6e68364ddbea8941faf5db",
              "size": 259856
            },
            "http://ports.ubuntu.com/pool/main/s/samba/libsmbclient_4.3.11+dfsg-0ubuntu0.16.04.21_ppc64el.deb": {
              "md5": "9cc7ddb5f7508abb3531a51f1478644f",
              "size": 49986
            },
            "http://ports.ubuntu.com/pool/universe/s/samba/libpam-winbind_4.3.11+dfsg-0ubuntu0.16.04.21_ppc64el.deb": {
              "md5": "0b5d2c4a885f530579c8d4fab99de473",
              "size": 27862
            },
            "http://ports.ubuntu.com/pool/universe/s/samba/samba-testsuite_4.3.11+dfsg-0ubuntu0.16.04.21_ppc64el.deb": {
              "md5": "6ac72894a11cfb90ef7b73c71c2cf9e1",
              "size": 1489590
            },
            "http://ports.ubuntu.com/pool/universe/s/samba/ctdb_4.3.11+dfsg-0ubuntu0.16.04.21_ppc64el.deb": {
              "md5": "5b6f1637d6d077d546b90504ce2927dd",
              "size": 408600
            },
            "http://ports.ubuntu.com/pool/universe/s/samba/libnss-winbind_4.3.11+dfsg-0ubuntu0.16.04.21_ppc64el.deb": {
              "md5": "77c079a8f3529de40720324607c401da",
              "size": 12132
            },
            "http://ports.ubuntu.com/pool/main/s/samba/libwbclient0_4.3.11+dfsg-0ubuntu0.16.04.21_ppc64el.deb": {
              "md5": "317c0792ff32450f011ab489e61aea9d",
              "size": 28870
            }
          }
        },
        "i386": {
          "urls": {
            "http://security.ubuntu.com/ubuntu/pool/main/s/samba/samba-common-bin_4.3.11+dfsg-0ubuntu0.16.04.21_i386.deb": {
              "md5": "24fff5ec998928449e043e77f3639965",
              "size": 543056
            },
            "http://security.ubuntu.com/ubuntu/pool/main/s/samba/samba-libs_4.3.11+dfsg-0ubuntu0.16.04.21_i386.deb": {
              "md5": "6fab308644639cc3e1b4da245f7c7491",
              "size": 5545520
            },
            "http://security.ubuntu.com/ubuntu/pool/universe/s/samba/libnss-winbind_4.3.11+dfsg-0ubuntu0.16.04.21_i386.deb": {
              "md5": "6527bb1d979547d9d294d6586f51ab47",
              "size": 13126
            },
            "http://security.ubuntu.com/ubuntu/pool/main/s/samba/samba-dev_4.3.11+dfsg-0ubuntu0.16.04.21_i386.deb": {
              "md5": "91100c5ebb6b36bbe4ab50f8195289b0",
              "size": 279924
            },
            "http://security.ubuntu.com/ubuntu/pool/universe/s/samba/samba-testsuite_4.3.11+dfsg-0ubuntu0.16.04.21_i386.deb": {
              "md5": "6c07b902f3d6dfc18ac1bcf2d0159b2c",
              "size": 1761438
            },
            "http://security.ubuntu.com/ubuntu/pool/main/s/samba/libwbclient0_4.3.11+dfsg-0ubuntu0.16.04.21_i386.deb": {
              "md5": "d5af104e29da654621a9fe8512cbe7c6",
              "size": 32836
            },
            "http://security.ubuntu.com/ubuntu/pool/main/s/samba/python-samba_4.3.11+dfsg-0ubuntu0.16.04.21_i386.deb": {
              "md5": "9b322f1108b7b2d0646de5bf0a65b0b7",
              "size": 990222
            },
            "http://security.ubuntu.com/ubuntu/pool/main/s/samba/smbclient_4.3.11+dfsg-0ubuntu0.16.04.21_i386.deb": {
              "md5": "b276d2c053e32248f980288b5ce020df",
              "size": 337568
            },
            "http://security.ubuntu.com/ubuntu/pool/universe/s/samba/ctdb_4.3.11+dfsg-0ubuntu0.16.04.21_i386.deb": {
              "md5": "616f8b9bb25bb4d0a9b8f2452cffb43e",
              "size": 447972
            },
            "http://security.ubuntu.com/ubuntu/pool/main/s/samba/libparse-pidl-perl_4.3.11+dfsg-0ubuntu0.16.04.21_i386.deb": {
              "md5": "ee2c2a594fba0d9bdc74261421a62365",
              "size": 95360
            },
            "http://security.ubuntu.com/ubuntu/pool/main/s/samba/samba-dbg_4.3.11+dfsg-0ubuntu0.16.04.21_i386.deb": {
              "md5": "91058dbe6675b6b35637ab1cac2bfe66",
              "size": 27262854
            },
            "http://security.ubuntu.com/ubuntu/pool/main/s/samba/winbind_4.3.11+dfsg-0ubuntu0.16.04.21_i386.deb": {
              "md5": "966877b11877b0f6538374c8243a22e2",
              "size": 449886
            },
            "http://security.ubuntu.com/ubuntu/pool/main/s/samba/samba-vfs-modules_4.3.11+dfsg-0ubuntu0.16.04.21_i386.deb": {
              "md5": "bbd4c75f76ecf7978fb6bea23a689f04",
              "size": 272846
            },
            "http://security.ubuntu.com/ubuntu/pool/main/s/samba/libsmbclient_4.3.11+dfsg-0ubuntu0.16.04.21_i386.deb": {
              "md5": "18fa184307aa60c642f5f01168e00416",
              "size": 57254
            },
            "http://security.ubuntu.com/ubuntu/pool/main/s/samba/libsmbclient-dev_4.3.11+dfsg-0ubuntu0.16.04.21_i386.deb": {
              "md5": "335f65ef4186d73d8c15dbb038e42c7d",
              "size": 40834
            },
            "http://security.ubuntu.com/ubuntu/pool/universe/s/samba/registry-tools_4.3.11+dfsg-0ubuntu0.16.04.21_i386.deb": {
              "md5": "3736a6587b65327656d3144c61fa8305",
              "size": 28386
            },
            "http://security.ubuntu.com/ubuntu/pool/main/s/samba/libwbclient-dev_4.3.11+dfsg-0ubuntu0.16.04.21_i386.deb": {
              "md5": "68541e1c8a4b2c545a36adf9eeecb6e7",
              "size": 12268
            },
            "http://security.ubuntu.com/ubuntu/pool/main/s/samba/samba-dsdb-modules_4.3.11+dfsg-0ubuntu0.16.04.21_i386.deb": {
              "md5": "585b910b6df6b4fc31c58bc42fa642a8",
              "size": 238550
            },
            "http://security.ubuntu.com/ubuntu/pool/main/s/samba/samba_4.3.11+dfsg-0ubuntu0.16.04.21_i386.deb": {
              "md5": "b340bfc781a6cb140b25852c4111b434",
              "size": 953156
            },
            "http://security.ubuntu.com/ubuntu/pool/universe/s/samba/libpam-winbind_4.3.11+dfsg-0ubuntu0.16.04.21_i386.deb": {
              "md5": "03b05543902275d300c32368298b0f47",
              "size": 30086
            }
          }
        },
        "powerpc": {
          "urls": {
            "http://ports.ubuntu.com/pool/main/s/samba/samba-vfs-modules_4.3.11+dfsg-0ubuntu0.16.04.21_powerpc.deb": {
              "md5": "3ebff0da5c06c677e705277b4c7f66d2",
              "size": 240880
            },
            "http://ports.ubuntu.com/pool/main/s/samba/samba-dbg_4.3.11+dfsg-0ubuntu0.16.04.21_powerpc.deb": {
              "md5": "cf6ac9ca70036c40187928172f3a7a04",
              "size": 35469058
            },
            "http://ports.ubuntu.com/pool/main/s/samba/winbind_4.3.11+dfsg-0ubuntu0.16.04.21_powerpc.deb": {
              "md5": "1cde1cc7797b58b0a30284603e4a2db7",
              "size": 378504
            },
            "http://ports.ubuntu.com/pool/main/s/samba/samba_4.3.11+dfsg-0ubuntu0.16.04.21_powerpc.deb": {
              "md5": "b07ac21610c07df05a9d9bbb1d5fdcf0",
              "size": 853758
            },
            "http://ports.ubuntu.com/pool/main/s/samba/libwbclient0_4.3.11+dfsg-0ubuntu0.16.04.21_powerpc.deb": {
              "md5": "7ca334c849cf53af2d66da8c9d900fb1",
              "size": 28342
            },
            "http://ports.ubuntu.com/pool/main/s/samba/samba-dev_4.3.11+dfsg-0ubuntu0.16.04.21_powerpc.deb": {
              "md5": "ef524977f928f154e2a09b4b715d8884",
              "size": 279914
            },
            "http://ports.ubuntu.com/pool/main/s/samba/samba-common-bin_4.3.11+dfsg-0ubuntu0.16.04.21_powerpc.deb": {
              "md5": "1d0c00dcde3142e8e3ce53d542030c2b",
              "size": 474852
            },
            "http://ports.ubuntu.com/pool/main/s/samba/libsmbclient-dev_4.3.11+dfsg-0ubuntu0.16.04.21_powerpc.deb": {
              "md5": "bf450a7e714f08234b2ee8866f1fbd80",
              "size": 40764
            },
            "http://ports.ubuntu.com/pool/universe/s/samba/ctdb_4.3.11+dfsg-0ubuntu0.16.04.21_powerpc.deb": {
              "md5": "09403a1e7c2871579d76f5d8aaef2102",
              "size": 390964
            },
            "http://ports.ubuntu.com/pool/main/s/samba/samba-dsdb-modules_4.3.11+dfsg-0ubuntu0.16.04.21_powerpc.deb": {
              "md5": "737b224d3bafce8e8c67c069129a2199",
              "size": 194256
            },
            "http://ports.ubuntu.com/pool/universe/s/samba/registry-tools_4.3.11+dfsg-0ubuntu0.16.04.21_powerpc.deb": {
              "md5": "b0cb7436255f64071b7bb3dd0422d97f",
              "size": 27028
            },
            "http://ports.ubuntu.com/pool/main/s/samba/libsmbclient_4.3.11+dfsg-0ubuntu0.16.04.21_powerpc.deb": {
              "md5": "6edf8549cba5784465f4bf098d0e7f20",
              "size": 48376
            },
            "http://ports.ubuntu.com/pool/main/s/samba/libparse-pidl-perl_4.3.11+dfsg-0ubuntu0.16.04.21_powerpc.deb": {
              "md5": "d87f4a9d282992799a7ce5155e3160b4",
              "size": 95734
            },
            "http://ports.ubuntu.com/pool/main/s/samba/samba-libs_4.3.11+dfsg-0ubuntu0.16.04.21_powerpc.deb": {
              "md5": "d5e75c53c1a3ff1a81b71455515c2d65",
              "size": 4467216
            },
            "http://ports.ubuntu.com/pool/main/s/samba/libwbclient-dev_4.3.11+dfsg-0ubuntu0.16.04.21_powerpc.deb": {
              "md5": "8984de72996c66f617c0e72cbd9d8cd8",
              "size": 12326
            },
            "http://ports.ubuntu.com/pool/main/s/samba/smbclient_4.3.11+dfsg-0ubuntu0.16.04.21_powerpc.deb": {
              "md5": "65b3fe12d721e281d9df6104c5e3bf5a",
              "size": 291348
            },
            "http://ports.ubuntu.com/pool/main/s/samba/python-samba_4.3.11+dfsg-0ubuntu0.16.04.21_powerpc.deb": {
              "md5": "01e1f17d64c462d3f5ec5d9264c5a1ca",
              "size": 830296
            },
            "http://ports.ubuntu.com/pool/universe/s/samba/libnss-winbind_4.3.11+dfsg-0ubuntu0.16.04.21_powerpc.deb": {
              "md5": "88cac6ce969ff8bc51586d6fe4a97079",
              "size": 11772
            },
            "http://ports.ubuntu.com/pool/universe/s/samba/libpam-winbind_4.3.11+dfsg-0ubuntu0.16.04.21_powerpc.deb": {
              "md5": "150534fc746dcfc454746048fc010c13",
              "size": 26796
            },
            "http://ports.ubuntu.com/pool/universe/s/samba/samba-testsuite_4.3.11+dfsg-0ubuntu0.16.04.21_powerpc.deb": {
              "md5": "00835361dd9788f3a98699843357b0d1",
              "size": 1445878
            }
          }
        },
        "source": {
          "urls": {
            "http://security.ubuntu.com/ubuntu/pool/main/s/samba/samba_4.3.11+dfsg-0ubuntu0.16.04.21.debian.tar.xz": {
              "md5": "9f376da13c6b346a9f47927422435d18",
              "size": 280912
            },
            "http://security.ubuntu.com/ubuntu/pool/main/s/samba/samba_4.3.11+dfsg-0ubuntu0.16.04.21.dsc": {
              "md5": "21d4df53038704deeb0633663cd7d466",
              "size": 4125
            },
            "http://security.ubuntu.com/ubuntu/pool/main/s/samba/samba_4.3.11+dfsg.orig.tar.xz": {
              "md5": "efc1f8f18fe55c5d2903fa18eabc39cf",
              "size": 14123020
            }
          }
        },
        "s390x": {
          "urls": {
            "http://ports.ubuntu.com/pool/universe/s/samba/libpam-winbind_4.3.11+dfsg-0ubuntu0.16.04.21_s390x.deb": {
              "md5": "54398cbad25daee344aebc5ab787a553",
              "size": 26942
            },
            "http://ports.ubuntu.com/pool/main/s/samba/libwbclient0_4.3.11+dfsg-0ubuntu0.16.04.21_s390x.deb": {
              "md5": "3ae25bd31ac671dd2ca666a497217424",
              "size": 29002
            },
            "http://ports.ubuntu.com/pool/universe/s/samba/registry-tools_4.3.11+dfsg-0ubuntu0.16.04.21_s390x.deb": {
              "md5": "5a12a43551547852140e6d9d5f17c077",
              "size": 28494
            },
            "http://ports.ubuntu.com/pool/main/s/samba/python-samba_4.3.11+dfsg-0ubuntu0.16.04.21_s390x.deb": {
              "md5": "22bfe08c0f713a3b49498d7368eea13e",
              "size": 1019328
            },
            "http://ports.ubuntu.com/pool/main/s/samba/samba_4.3.11+dfsg-0ubuntu0.16.04.21_s390x.deb": {
              "md5": "5973334d8eaa0a8e8f99c2476e2f7b05",
              "size": 862948
            },
            "http://ports.ubuntu.com/pool/main/s/samba/samba-dbg_4.3.11+dfsg-0ubuntu0.16.04.21_s390x.deb": {
              "md5": "5c82caac81356077fea26dd342e75752",
              "size": 34110564
            },
            "http://ports.ubuntu.com/pool/universe/s/samba/ctdb_4.3.11+dfsg-0ubuntu0.16.04.21_s390x.deb": {
              "md5": "59e339dc52bd7224261c0c9cf21ef5c4",
              "size": 403342
            },
            "http://ports.ubuntu.com/pool/universe/s/samba/libnss-winbind_4.3.11+dfsg-0ubuntu0.16.04.21_s390x.deb": {
              "md5": "bd50eec44a560a0b4c76aa998c07e137",
              "size": 12210
            },
            "http://ports.ubuntu.com/pool/main/s/samba/libsmbclient-dev_4.3.11+dfsg-0ubuntu0.16.04.21_s390x.deb": {
              "md5": "09f37128a342c08f20a028d9d2536748",
              "size": 40820
            },
            "http://ports.ubuntu.com/pool/main/s/samba/samba-libs_4.3.11+dfsg-0ubuntu0.16.04.21_s390x.deb": {
              "md5": "616eee2954b22abf2ffb0eda5d7ac221",
              "size": 4760700
            },
            "http://ports.ubuntu.com/pool/main/s/samba/samba-common-bin_4.3.11+dfsg-0ubuntu0.16.04.21_s390x.deb": {
              "md5": "7823ca92ef7714f25056030319db2757",
              "size": 486318
            },
            "http://ports.ubuntu.com/pool/main/s/samba/winbind_4.3.11+dfsg-0ubuntu0.16.04.21_s390x.deb": {
              "md5": "63a70ca4c1c92af7df34e31c485542d4",
              "size": 385884
            },
            "http://ports.ubuntu.com/pool/main/s/samba/samba-vfs-modules_4.3.11+dfsg-0ubuntu0.16.04.21_s390x.deb": {
              "md5": "5c9019f000fa81c64ba3c9616d9bdfb2",
              "size": 247728
            },
            "http://ports.ubuntu.com/pool/main/s/samba/samba-dsdb-modules_4.3.11+dfsg-0ubuntu0.16.04.21_s390x.deb": {
              "md5": "36963fe99e2a5da5494eb939abcf176a",
              "size": 204816
            },
            "http://ports.ubuntu.com/pool/main/s/samba/libparse-pidl-perl_4.3.11+dfsg-0ubuntu0.16.04.21_s390x.deb": {
              "md5": "01395cb8da74f11df005c0ea1aefba2c",
              "size": 95692
            },
            "http://ports.ubuntu.com/pool/main/s/samba/libsmbclient_4.3.11+dfsg-0ubuntu0.16.04.21_s390x.deb": {
              "md5": "890de319eee89ad609772f588803d621",
              "size": 49774
            },
            "http://ports.ubuntu.com/pool/main/s/samba/libwbclient-dev_4.3.11+dfsg-0ubuntu0.16.04.21_s390x.deb": {
              "md5": "b2b52706c89602da65c5cfb25f54d512",
              "size": 12278
            },
            "http://ports.ubuntu.com/pool/universe/s/samba/samba-testsuite_4.3.11+dfsg-0ubuntu0.16.04.21_s390x.deb": {
              "md5": "9657f4701d194fbbcdaa2a233dec781f",
              "size": 1478394
            },
            "http://ports.ubuntu.com/pool/main/s/samba/samba-dev_4.3.11+dfsg-0ubuntu0.16.04.21_s390x.deb": {
              "md5": "c5ab2036ad5c2199a212e44bc545a4a6",
              "size": 279832
            },
            "http://ports.ubuntu.com/pool/main/s/samba/smbclient_4.3.11+dfsg-0ubuntu0.16.04.21_s390x.deb": {
              "md5": "7131b48318d189ffead8d395bc64636b",
              "size": 299158
            }
          }
        },
        "armhf": {
          "urls": {
            "http://ports.ubuntu.com/pool/main/s/samba/libsmbclient-dev_4.3.11+dfsg-0ubuntu0.16.04.21_armhf.deb": {
              "md5": "202d8f9b53ffb04af0a7171d2849ac5a",
              "size": 40836
            },
            "http://ports.ubuntu.com/pool/universe/s/samba/libpam-winbind_4.3.11+dfsg-0ubuntu0.16.04.21_armhf.deb": {
              "md5": "ade40fe8a5176231499982b01ba53a75",
              "size": 25262
            },
            "http://ports.ubuntu.com/pool/main/s/samba/winbind_4.3.11+dfsg-0ubuntu0.16.04.21_armhf.deb": {
              "md5": "da67ca2d945237153c50180fa6975198",
              "size": 370620
            },
            "http://ports.ubuntu.com/pool/universe/s/samba/libnss-winbind_4.3.11+dfsg-0ubuntu0.16.04.21_armhf.deb": {
              "md5": "717259dc6507628127af77e660118231",
              "size": 11448
            },
            "http://ports.ubuntu.com/pool/main/s/samba/smbclient_4.3.11+dfsg-0ubuntu0.16.04.21_armhf.deb": {
              "md5": "0358f0e743cacc4501875b590b8b0a94",
              "size": 277686
            },
            "http://ports.ubuntu.com/pool/main/s/samba/samba-libs_4.3.11+dfsg-0ubuntu0.16.04.21_armhf.deb": {
              "md5": "631fb5debae79ac0d0f05f10620815d7",
              "size": 4429958
            },
            "http://ports.ubuntu.com/pool/main/s/samba/samba-dbg_4.3.11+dfsg-0ubuntu0.16.04.21_armhf.deb": {
              "md5": "59951bac2738cea77f69c57c872497bb",
              "size": 32390800
            },
            "http://ports.ubuntu.com/pool/main/s/samba/samba-dev_4.3.11+dfsg-0ubuntu0.16.04.21_armhf.deb": {
              "md5": "df15416a071bceb9817af24da2e35080",
              "size": 279776
            },
            "http://ports.ubuntu.com/pool/universe/s/samba/registry-tools_4.3.11+dfsg-0ubuntu0.16.04.21_armhf.deb": {
              "md5": "3505b1e64eb3b547ebd2cf9cfcf45b93",
              "size": 25896
            },
            "http://ports.ubuntu.com/pool/main/s/samba/samba-dsdb-modules_4.3.11+dfsg-0ubuntu0.16.04.21_armhf.deb": {
              "md5": "8b0a257c457583ae3a7be407a2ab3694",
              "size": 195780
            },
            "http://ports.ubuntu.com/pool/universe/s/samba/ctdb_4.3.11+dfsg-0ubuntu0.16.04.21_armhf.deb": {
              "md5": "15dcf402a4353605eca2a4713228e163",
              "size": 405172
            },
            "http://ports.ubuntu.com/pool/main/s/samba/python-samba_4.3.11+dfsg-0ubuntu0.16.04.21_armhf.deb": {
              "md5": "a0ad4fa56bb9510732000a26b3716b1a",
              "size": 879866
            },
            "http://ports.ubuntu.com/pool/main/s/samba/samba_4.3.11+dfsg-0ubuntu0.16.04.21_armhf.deb": {
              "md5": "18f4378a42fd70988a484a102f628be9",
              "size": 841806
            },
            "http://ports.ubuntu.com/pool/universe/s/samba/samba-testsuite_4.3.11+dfsg-0ubuntu0.16.04.21_armhf.deb": {
              "md5": "9ea0f26513c102566244fc60fb0445bf",
              "size": 1617338
            },
            "http://ports.ubuntu.com/pool/main/s/samba/samba-common-bin_4.3.11+dfsg-0ubuntu0.16.04.21_armhf.deb": {
              "md5": "49088b7da4143db553a9d854a2dde33b",
              "size": 467724
            },
            "http://ports.ubuntu.com/pool/main/s/samba/libwbclient0_4.3.11+dfsg-0ubuntu0.16.04.21_armhf.deb": {
              "md5": "d17f24579f17c3c7dd8e0c34be4add39",
              "size": 26786
            },
            "http://ports.ubuntu.com/pool/main/s/samba/libparse-pidl-perl_4.3.11+dfsg-0ubuntu0.16.04.21_armhf.deb": {
              "md5": "3e7cb75719e18c52e3c82a1510eeff91",
              "size": 95638
            },
            "http://ports.ubuntu.com/pool/main/s/samba/libwbclient-dev_4.3.11+dfsg-0ubuntu0.16.04.21_armhf.deb": {
              "md5": "cc4e51ca31aec1c59b426a3b26505ec7",
              "size": 12334
            },
            "http://ports.ubuntu.com/pool/main/s/samba/libsmbclient_4.3.11+dfsg-0ubuntu0.16.04.21_armhf.deb": {
              "md5": "8e606f19fcaa095d53845d68e37bc973",
              "size": 47414
            },
            "http://ports.ubuntu.com/pool/main/s/samba/samba-vfs-modules_4.3.11+dfsg-0ubuntu0.16.04.21_armhf.deb": {
              "md5": "915dc50a139575a0f1d33c78de50dbe4",
              "size": 236214
            }
          }
        },
        "arm64": {
          "urls": {
            "http://ports.ubuntu.com/pool/main/s/samba/samba-dbg_4.3.11+dfsg-0ubuntu0.16.04.21_arm64.deb": {
              "md5": "1677abe028f95b6459079f92930438e1",
              "size": 34632456
            },
            "http://ports.ubuntu.com/pool/main/s/samba/libwbclient-dev_4.3.11+dfsg-0ubuntu0.16.04.21_arm64.deb": {
              "md5": "2104a7f67d4a22da6be2ba992ee8dca3",
              "size": 12338
            },
            "http://ports.ubuntu.com/pool/universe/s/samba/samba-testsuite_4.3.11+dfsg-0ubuntu0.16.04.21_arm64.deb": {
              "md5": "94a72c0217f7d68f0f80c97710b22141",
              "size": 1372494
            },
            "http://ports.ubuntu.com/pool/universe/s/samba/ctdb_4.3.11+dfsg-0ubuntu0.16.04.21_arm64.deb": {
              "md5": "aef409a476831920a4e57cdf1fde6c03",
              "size": 379330
            },
            "http://ports.ubuntu.com/pool/main/s/samba/libsmbclient_4.3.11+dfsg-0ubuntu0.16.04.21_arm64.deb": {
              "md5": "88ec61ada0ff00a806a45f19ad81acd5",
              "size": 44730
            },
            "http://ports.ubuntu.com/pool/main/s/samba/samba-dev_4.3.11+dfsg-0ubuntu0.16.04.21_arm64.deb": {
              "md5": "8df45081a9dab4d89f1f00dbe0120fa6",
              "size": 279778
            },
            "http://ports.ubuntu.com/pool/main/s/samba/libparse-pidl-perl_4.3.11+dfsg-0ubuntu0.16.04.21_arm64.deb": {
              "md5": "e78dda7301a3a0a14d2514d953cdd23b",
              "size": 95628
            },
            "http://ports.ubuntu.com/pool/main/s/samba/libsmbclient-dev_4.3.11+dfsg-0ubuntu0.16.04.21_arm64.deb": {
              "md5": "1ee3c5f27ea74e9c9d67892421656213",
              "size": 40840
            },
            "http://ports.ubuntu.com/pool/main/s/samba/smbclient_4.3.11+dfsg-0ubuntu0.16.04.21_arm64.deb": {
              "md5": "16a28352b38cdaa31b53c9cf8634a284",
              "size": 269844
            },
            "http://ports.ubuntu.com/pool/main/s/samba/samba-vfs-modules_4.3.11+dfsg-0ubuntu0.16.04.21_arm64.deb": {
              "md5": "16f0d1fcc53971ab3adabe2288099d61",
              "size": 226086
            },
            "http://ports.ubuntu.com/pool/main/s/samba/winbind_4.3.11+dfsg-0ubuntu0.16.04.21_arm64.deb": {
              "md5": "4f83804e810aa8a87e217151e2a16ef2",
              "size": 351642
            },
            "http://ports.ubuntu.com/pool/main/s/samba/samba-common-bin_4.3.11+dfsg-0ubuntu0.16.04.21_arm64.deb": {
              "md5": "f9747329273aa71d8de3d899b5a0f9f4",
              "size": 448042
            },
            "http://ports.ubuntu.com/pool/main/s/samba/libwbclient0_4.3.11+dfsg-0ubuntu0.16.04.21_arm64.deb": {
              "md5": "138177bca57932354d5c6253e9e4abd7",
              "size": 26604
            },
            "http://ports.ubuntu.com/pool/universe/s/samba/libnss-winbind_4.3.11+dfsg-0ubuntu0.16.04.21_arm64.deb": {
              "md5": "3f7e4e25f3b8c63175f280dbc8c5b55b",
              "size": 11290
            },
            "http://ports.ubuntu.com/pool/main/s/samba/samba_4.3.11+dfsg-0ubuntu0.16.04.21_arm64.deb": {
              "md5": "c866a63544176a213edb864083d97fce",
              "size": 813826
            },
            "http://ports.ubuntu.com/pool/universe/s/samba/libpam-winbind_4.3.11+dfsg-0ubuntu0.16.04.21_arm64.deb": {
              "md5": "46af6e348164a9edb7aefce298b328b8",
              "size": 25736
            },
            "http://ports.ubuntu.com/pool/universe/s/samba/registry-tools_4.3.11+dfsg-0ubuntu0.16.04.21_arm64.deb": {
              "md5": "67f03112cc58113b39a4657298dcf961",
              "size": 25876
            },
            "http://ports.ubuntu.com/pool/main/s/samba/python-samba_4.3.11+dfsg-0ubuntu0.16.04.21_arm64.deb": {
              "md5": "2f404b438b702a424b0710209eb1285f",
              "size": 814666
            },
            "http://ports.ubuntu.com/pool/main/s/samba/samba-dsdb-modules_4.3.11+dfsg-0ubuntu0.16.04.21_arm64.deb": {
              "md5": "b57e69f157365eec8d6f501424ea77a9",
              "size": 183608
            },
            "http://ports.ubuntu.com/pool/main/s/samba/samba-libs_4.3.11+dfsg-0ubuntu0.16.04.21_arm64.deb": {
              "md5": "39913d99ecb43c63aa29921e1c484a67",
              "size": 4209844
            }
          }
        }
      },
      "sources": {
        "samba": {
          "version": "2:4.3.11+dfsg-0ubuntu0.16.04.21",
          "description": "SMB/CIFS file, print, and login server for Unix"
        }
      }
    }
  },
  "title": "Samba regression",
  "timestamp": 1558957185.17483,
  "summary": "samba regression",
  "action": "In general, a standard system update will make all the necessary changes.\n",
  "isummary": "USN-3976-1 introduced a regression in Samba.\n",
  "id": "USN-3976-3",
  "cves": [
    "https://launchpad.net/bugs/1827924"
  ]
}