{
  "description": "It was discovered that Apport could be tricked into writing core files as\nroot into arbitrary directories in certain scenarios. A local attacker\ncould possibly use this issue to escalate privileges. This update will\ncause Apport to generate all core files in the /var/lib/apport/coredump\ndirectory.\n",
  "releases": {
    "hirsute": {
      "allbinaries": {
        "python3-problem-report": {
          "pocket": "security",
          "source": "apport",
          "version": "2.20.11-0ubuntu65.4"
        },
        "apport-kde": {
          "pocket": "security",
          "source": "apport",
          "version": "2.20.11-0ubuntu65.4"
        },
        "apport-retrace": {
          "pocket": "security",
          "source": "apport",
          "version": "2.20.11-0ubuntu65.4"
        },
        "apport-valgrind": {
          "pocket": "security",
          "source": "apport",
          "version": "2.20.11-0ubuntu65.4"
        },
        "python3-apport": {
          "pocket": "security",
          "source": "apport",
          "version": "2.20.11-0ubuntu65.4"
        },
        "dh-apport": {
          "pocket": "security",
          "source": "apport",
          "version": "2.20.11-0ubuntu65.4"
        },
        "apport-gtk": {
          "pocket": "security",
          "source": "apport",
          "version": "2.20.11-0ubuntu65.4"
        },
        "apport": {
          "pocket": "security",
          "source": "apport",
          "version": "2.20.11-0ubuntu65.4"
        },
        "apport-noui": {
          "pocket": "security",
          "source": "apport",
          "version": "2.20.11-0ubuntu65.4"
        }
      },
      "binaries": {
        "apport": {
          "pocket": "security",
          "version": "2.20.11-0ubuntu65.4"
        },
        "python3-apport": {
          "pocket": "security",
          "version": "2.20.11-0ubuntu65.4"
        }
      },
      "archs": {
        "source": {
          "urls": {
            "http://security.ubuntu.com/ubuntu/pool/main/a/apport/apport_2.20.11-0ubuntu65.4.tar.gz": {
              "md5": "fb173c608a6626bdd24b9e16340b5857",
              "size": 1406395
            },
            "http://security.ubuntu.com/ubuntu/pool/main/a/apport/apport_2.20.11-0ubuntu65.4.dsc": {
              "md5": "a1d9ac5fc781f0c88ccbe514bb8a8888",
              "size": 2629
            }
          }
        },
        "all": {
          "urls": {
            "http://security.ubuntu.com/ubuntu/pool/main/a/apport/apport-gtk_2.20.11-0ubuntu65.4_all.deb": {
              "md5": "428f97121a07b7d092bdc5f4fdce6725",
              "size": 9728
            },
            "http://security.ubuntu.com/ubuntu/pool/main/a/apport/apport_2.20.11-0ubuntu65.4_all.deb": {
              "md5": "d629fb4da0f4308c8107aea0bce81f43",
              "size": 129040
            },
            "http://security.ubuntu.com/ubuntu/pool/universe/a/apport/apport-kde_2.20.11-0ubuntu65.4_all.deb": {
              "md5": "db7b5a2d474fa0b9c4dcdd54e796b282",
              "size": 17884
            },
            "http://security.ubuntu.com/ubuntu/pool/universe/a/apport/apport-noui_2.20.11-0ubuntu65.4_all.deb": {
              "md5": "8d51d0f877fd051e57eb246b2770eece",
              "size": 1964
            },
            "http://security.ubuntu.com/ubuntu/pool/main/a/apport/python3-problem-report_2.20.11-0ubuntu65.4_all.deb": {
              "md5": "11535c96fc2aed796fb0030b141e8543",
              "size": 9640
            },
            "http://security.ubuntu.com/ubuntu/pool/universe/a/apport/apport-valgrind_2.20.11-0ubuntu65.4_all.deb": {
              "md5": "ab2013af03cfe188abb98fff44aa5462",
              "size": 5180
            },
            "http://security.ubuntu.com/ubuntu/pool/main/a/apport/python3-apport_2.20.11-0ubuntu65.4_all.deb": {
              "md5": "08af1f7f15987b3ec6d247faa081fa77",
              "size": 86056
            },
            "http://security.ubuntu.com/ubuntu/pool/universe/a/apport/dh-apport_2.20.11-0ubuntu65.4_all.deb": {
              "md5": "39ac107b926f44dd07b42c633ddc129c",
              "size": 6728
            },
            "http://security.ubuntu.com/ubuntu/pool/main/a/apport/apport-retrace_2.20.11-0ubuntu65.4_all.deb": {
              "md5": "e587d6c88a588c2b2b27bf7370042344",
              "size": 13092
            }
          }
        }
      },
      "sources": {
        "apport": {
          "version": "2.20.11-0ubuntu65.4",
          "description": "automatically generate crash reports for debugging"
        }
      }
    },
    "impish": {
      "allbinaries": {
        "python3-problem-report": {
          "pocket": "security",
          "source": "apport",
          "version": "2.20.11-0ubuntu71"
        },
        "apport-kde": {
          "pocket": "security",
          "source": "apport",
          "version": "2.20.11-0ubuntu71"
        },
        "apport-retrace": {
          "pocket": "security",
          "source": "apport",
          "version": "2.20.11-0ubuntu71"
        },
        "apport-valgrind": {
          "pocket": "security",
          "source": "apport",
          "version": "2.20.11-0ubuntu71"
        },
        "python3-apport": {
          "pocket": "security",
          "source": "apport",
          "version": "2.20.11-0ubuntu71"
        },
        "dh-apport": {
          "pocket": "security",
          "source": "apport",
          "version": "2.20.11-0ubuntu71"
        },
        "apport-gtk": {
          "pocket": "security",
          "source": "apport",
          "version": "2.20.11-0ubuntu71"
        },
        "apport": {
          "pocket": "security",
          "source": "apport",
          "version": "2.20.11-0ubuntu71"
        },
        "apport-noui": {
          "pocket": "security",
          "source": "apport",
          "version": "2.20.11-0ubuntu71"
        }
      },
      "binaries": {
        "apport": {
          "pocket": "security",
          "version": "2.20.11-0ubuntu71"
        },
        "python3-apport": {
          "pocket": "security",
          "version": "2.20.11-0ubuntu71"
        }
      },
      "archs": {
        "source": {
          "urls": {
            "http://security.ubuntu.com/ubuntu/pool/main/a/apport/apport_2.20.11-0ubuntu71.tar.gz": {
              "md5": "62d98888bb7c451d4dc693ade2081ede",
              "size": 1406652
            },
            "http://security.ubuntu.com/ubuntu/pool/main/a/apport/apport_2.20.11-0ubuntu71.dsc": {
              "md5": "ce7cd0296a103497e06d168b063ed4da",
              "size": 2621
            }
          }
        },
        "all": {
          "urls": {
            "http://security.ubuntu.com/ubuntu/pool/main/a/apport/apport-gtk_2.20.11-0ubuntu71_all.deb": {
              "md5": "18e6f558a164dac43f67a108999888f9",
              "size": 9580
            },
            "http://security.ubuntu.com/ubuntu/pool/universe/a/apport/apport-kde_2.20.11-0ubuntu71_all.deb": {
              "md5": "29c86818b4bcba4755f6b8dbfb76869f",
              "size": 18692
            },
            "http://security.ubuntu.com/ubuntu/pool/main/a/apport/apport-retrace_2.20.11-0ubuntu71_all.deb": {
              "md5": "476766f06fe42f6a32272e43f8148969",
              "size": 13308
            },
            "http://security.ubuntu.com/ubuntu/pool/main/a/apport/python3-problem-report_2.20.11-0ubuntu71_all.deb": {
              "md5": "6bc679e03ac5d3a28ada32a08bff3d0e",
              "size": 9882
            },
            "http://security.ubuntu.com/ubuntu/pool/universe/a/apport/apport-valgrind_2.20.11-0ubuntu71_all.deb": {
              "md5": "f41d61ca9c8a8dc3776f36b9f3c1c9c2",
              "size": 5162
            },
            "http://security.ubuntu.com/ubuntu/pool/universe/a/apport/dh-apport_2.20.11-0ubuntu71_all.deb": {
              "md5": "141df6b536520df95fc2854df42bd724",
              "size": 6782
            },
            "http://security.ubuntu.com/ubuntu/pool/main/a/apport/apport_2.20.11-0ubuntu71_all.deb": {
              "md5": "92c741205313159e03aec6f784b4adcf",
              "size": 131722
            },
            "http://security.ubuntu.com/ubuntu/pool/main/a/apport/python3-apport_2.20.11-0ubuntu71_all.deb": {
              "md5": "8676715dd6d6b8435ed196f8b09f117c",
              "size": 87270
            },
            "http://security.ubuntu.com/ubuntu/pool/universe/a/apport/apport-noui_2.20.11-0ubuntu71_all.deb": {
              "md5": "6b069de088abc53f407ff5431712a6e1",
              "size": 1750
            }
          }
        }
      },
      "sources": {
        "apport": {
          "version": "2.20.11-0ubuntu71",
          "description": "automatically generate crash reports for debugging"
        }
      }
    },
    "bionic": {
      "allbinaries": {
        "apport": {
          "pocket": "security",
          "source": "apport",
          "version": "2.20.9-0ubuntu7.27"
        },
        "python3-problem-report": {
          "pocket": "security",
          "source": "apport",
          "version": "2.20.9-0ubuntu7.27"
        },
        "apport-kde": {
          "pocket": "security",
          "source": "apport",
          "version": "2.20.9-0ubuntu7.27"
        },
        "apport-retrace": {
          "pocket": "security",
          "source": "apport",
          "version": "2.20.9-0ubuntu7.27"
        },
        "apport-valgrind": {
          "pocket": "security",
          "source": "apport",
          "version": "2.20.9-0ubuntu7.27"
        },
        "python3-apport": {
          "pocket": "security",
          "source": "apport",
          "version": "2.20.9-0ubuntu7.27"
        },
        "dh-apport": {
          "pocket": "security",
          "source": "apport",
          "version": "2.20.9-0ubuntu7.27"
        },
        "apport-gtk": {
          "pocket": "security",
          "source": "apport",
          "version": "2.20.9-0ubuntu7.27"
        },
        "python-apport": {
          "pocket": "security",
          "source": "apport",
          "version": "2.20.9-0ubuntu7.27"
        },
        "python-problem-report": {
          "pocket": "security",
          "source": "apport",
          "version": "2.20.9-0ubuntu7.27"
        },
        "apport-noui": {
          "pocket": "security",
          "source": "apport",
          "version": "2.20.9-0ubuntu7.27"
        }
      },
      "binaries": {
        "apport": {
          "pocket": "security",
          "version": "2.20.9-0ubuntu7.27"
        },
        "python3-apport": {
          "pocket": "security",
          "version": "2.20.9-0ubuntu7.27"
        }
      },
      "archs": {
        "source": {
          "urls": {
            "http://security.ubuntu.com/ubuntu/pool/main/a/apport/apport_2.20.9-0ubuntu7.27.dsc": {
              "md5": "68c50b3b08d60adab6a848e7b848563f",
              "size": 2835
            },
            "http://security.ubuntu.com/ubuntu/pool/main/a/apport/apport_2.20.9-0ubuntu7.27.tar.gz": {
              "md5": "06953b81fd343d480d2606f281f8aa40",
              "size": 1370748
            }
          }
        },
        "all": {
          "urls": {
            "http://security.ubuntu.com/ubuntu/pool/main/a/apport/apport-gtk_2.20.9-0ubuntu7.27_all.deb": {
              "md5": "f7c494bb1b846669577e312ea0bf1285",
              "size": 9700
            },
            "http://security.ubuntu.com/ubuntu/pool/universe/a/apport/python-apport_2.20.9-0ubuntu7.27_all.deb": {
              "md5": "da3eb015cf2a6c03fad45b79522ad20c",
              "size": 83320
            },
            "http://security.ubuntu.com/ubuntu/pool/main/a/apport/python3-problem-report_2.20.9-0ubuntu7.27_all.deb": {
              "md5": "6778f6dc02bb21166392fb43e51a63a8",
              "size": 10004
            },
            "http://security.ubuntu.com/ubuntu/pool/universe/a/apport/dh-apport_2.20.9-0ubuntu7.27_all.deb": {
              "md5": "5de8fd3cd09bb9fede7bf76bcbd883ad",
              "size": 7008
            },
            "http://security.ubuntu.com/ubuntu/pool/universe/a/apport/apport-kde_2.20.9-0ubuntu7.27_all.deb": {
              "md5": "77caf2d99dde236199fe9e2e4e4e2542",
              "size": 17860
            },
            "http://security.ubuntu.com/ubuntu/pool/main/a/apport/apport-retrace_2.20.9-0ubuntu7.27_all.deb": {
              "md5": "c130d553f6e8cee56db7a737ef5f5593",
              "size": 13088
            },
            "http://security.ubuntu.com/ubuntu/pool/universe/a/apport/python-problem-report_2.20.9-0ubuntu7.27_all.deb": {
              "md5": "7d816e28b2d60aea26a830bf28bcd677",
              "size": 9912
            },
            "http://security.ubuntu.com/ubuntu/pool/universe/a/apport/apport-noui_2.20.9-0ubuntu7.27_all.deb": {
              "md5": "708b12a314ac896b40e70e62ec34a04a",
              "size": 1952
            },
            "http://security.ubuntu.com/ubuntu/pool/main/a/apport/python3-apport_2.20.9-0ubuntu7.27_all.deb": {
              "md5": "bd546641c3c7442ca51df34fea829151",
              "size": 83404
            },
            "http://security.ubuntu.com/ubuntu/pool/main/a/apport/apport_2.20.9-0ubuntu7.27_all.deb": {
              "md5": "b4b0bf26a872c4cbdd66272ec9e70d8b",
              "size": 125140
            },
            "http://security.ubuntu.com/ubuntu/pool/universe/a/apport/apport-valgrind_2.20.9-0ubuntu7.27_all.deb": {
              "md5": "cd805eb99d20a58b048139ff55e89226",
              "size": 5176
            }
          }
        }
      },
      "sources": {
        "apport": {
          "version": "2.20.9-0ubuntu7.27",
          "description": "automatically generate crash reports for debugging"
        }
      }
    },
    "focal": {
      "allbinaries": {
        "python3-problem-report": {
          "pocket": "security",
          "source": "apport",
          "version": "2.20.11-0ubuntu27.21"
        },
        "apport-kde": {
          "pocket": "security",
          "source": "apport",
          "version": "2.20.11-0ubuntu27.21"
        },
        "apport-retrace": {
          "pocket": "security",
          "source": "apport",
          "version": "2.20.11-0ubuntu27.21"
        },
        "apport-valgrind": {
          "pocket": "security",
          "source": "apport",
          "version": "2.20.11-0ubuntu27.21"
        },
        "python3-apport": {
          "pocket": "security",
          "source": "apport",
          "version": "2.20.11-0ubuntu27.21"
        },
        "dh-apport": {
          "pocket": "security",
          "source": "apport",
          "version": "2.20.11-0ubuntu27.21"
        },
        "apport-gtk": {
          "pocket": "security",
          "source": "apport",
          "version": "2.20.11-0ubuntu27.21"
        },
        "apport": {
          "pocket": "security",
          "source": "apport",
          "version": "2.20.11-0ubuntu27.21"
        },
        "apport-noui": {
          "pocket": "security",
          "source": "apport",
          "version": "2.20.11-0ubuntu27.21"
        }
      },
      "binaries": {
        "apport": {
          "pocket": "security",
          "version": "2.20.11-0ubuntu27.21"
        },
        "python3-apport": {
          "pocket": "security",
          "version": "2.20.11-0ubuntu27.21"
        }
      },
      "archs": {
        "source": {
          "urls": {
            "http://security.ubuntu.com/ubuntu/pool/main/a/apport/apport_2.20.11-0ubuntu27.21.dsc": {
              "md5": "11ddb57f721d299a7a0d536fda1671f6",
              "size": 2671
            },
            "http://security.ubuntu.com/ubuntu/pool/main/a/apport/apport_2.20.11-0ubuntu27.21.tar.gz": {
              "md5": "82517f559fd82a8cd67b11b2bb48da4f",
              "size": 1403106
            }
          }
        },
        "all": {
          "urls": {
            "http://security.ubuntu.com/ubuntu/pool/main/a/apport/python3-apport_2.20.11-0ubuntu27.21_all.deb": {
              "md5": "91d05e79cf88008db05a1179c5552705",
              "size": 85876
            },
            "http://security.ubuntu.com/ubuntu/pool/main/a/apport/apport-gtk_2.20.11-0ubuntu27.21_all.deb": {
              "md5": "36d3619b939bc823b308a8501c9590c0",
              "size": 9732
            },
            "http://security.ubuntu.com/ubuntu/pool/main/a/apport/apport_2.20.11-0ubuntu27.21_all.deb": {
              "md5": "ff7ead2ede15e37a21d6e7943a323dd4",
              "size": 128732
            },
            "http://security.ubuntu.com/ubuntu/pool/main/a/apport/apport-retrace_2.20.11-0ubuntu27.21_all.deb": {
              "md5": "e6ffb6e160e4da463280eaefee9a2569",
              "size": 13092
            },
            "http://security.ubuntu.com/ubuntu/pool/main/a/apport/python3-problem-report_2.20.11-0ubuntu27.21_all.deb": {
              "md5": "8a53826ec227a030601f7b30da4c45f8",
              "size": 9896
            },
            "http://security.ubuntu.com/ubuntu/pool/universe/a/apport/apport-noui_2.20.11-0ubuntu27.21_all.deb": {
              "md5": "34b6a95d401efff4b198fc6443696511",
              "size": 1968
            },
            "http://security.ubuntu.com/ubuntu/pool/universe/a/apport/apport-kde_2.20.11-0ubuntu27.21_all.deb": {
              "md5": "691b501287302acaa54b5ddd0e730f15",
              "size": 17896
            },
            "http://security.ubuntu.com/ubuntu/pool/universe/a/apport/dh-apport_2.20.11-0ubuntu27.21_all.deb": {
              "md5": "4c2edb6298155cefc601add2183c9352",
              "size": 6976
            },
            "http://security.ubuntu.com/ubuntu/pool/universe/a/apport/apport-valgrind_2.20.11-0ubuntu27.21_all.deb": {
              "md5": "420abcef7dbbe7f15d9390f139907031",
              "size": 5188
            }
          }
        }
      },
      "sources": {
        "apport": {
          "version": "2.20.11-0ubuntu27.21",
          "description": "automatically generate crash reports for debugging"
        }
      }
    }
  },
  "title": "Apport vulnerability",
  "timestamp": 1635159363.9746463,
  "summary": "apport vulnerability",
  "action": "In general, a standard system update will make all the necessary changes.\n",
  "isummary": "Apport could be made to create files as the administrator.\n",
  "id": "USN-5122-1",
  "cves": [
    "https://launchpad.net/bugs/1948657"
  ]
}