{
  "description": "The SuSE Security Team discovered several buffer overflows in the\nOpenSLP server and client library. By sending specially crafted SLP\npackets, a remote attacker could exploit this to crash the SLP server\nor execute arbitrary code with the privileges of the \"daemon\" user.\nLikewise, a malicious SLP server could exploit the client library\nvulnerabilities to execute arbitrary code with the privileges of the\nuser running the SLP client application.",
  "releases": {
    "warty": {
      "binaries": {
        "slpd": {
          "version": ""
        },
        "libslp1": {
          "version": ""
        }
      },
      "archs": {
        "source": {
          "urls": {
            "http://security.ubuntu.com/ubuntu/pool/main/o/openslp/openslp_1.0.11.orig.tar.gz": {
              "size": 608138,
              "md5": "0ec965956ad1f66850f050b19c828b55"
            },
            "http://security.ubuntu.com/ubuntu/pool/main/o/openslp/openslp_1.0.11-7ubuntu0.1.dsc": {
              "size": 655,
              "md5": "5ff8151d34a2b861a3d9f614072b92ca"
            },
            "http://security.ubuntu.com/ubuntu/pool/main/o/openslp/openslp_1.0.11-7ubuntu0.1.diff.gz": {
              "size": 151039,
              "md5": "eb727a65716e86e757e34748aa24cc45"
            }
          }
        },
        "all": {
          "urls": {
            "http://security.ubuntu.com/ubuntu/pool/main/o/openslp/openslp-doc_1.0.11-7ubuntu0.1_all.deb": {
              "size": 95946,
              "md5": "dffab2db867d3604939d692ffb3904f7"
            }
          }
        },
        "powerpc": {
          "urls": {
            "http://security.ubuntu.com/ubuntu/pool/main/o/openslp/libslp-dev_1.0.11-7ubuntu0.1_powerpc.deb": {
              "size": 66202,
              "md5": "ad95b923ad7b89cadb37972ccbe10443"
            },
            "http://security.ubuntu.com/ubuntu/pool/universe/o/openslp/slptool_1.0.11-7ubuntu0.1_powerpc.deb": {
              "size": 28076,
              "md5": "f507323a5ffa3082f34f610f911fd05a"
            },
            "http://security.ubuntu.com/ubuntu/pool/universe/o/openslp/slpd_1.0.11-7ubuntu0.1_powerpc.deb": {
              "size": 72190,
              "md5": "08e568c75979eaa01619668b6b68d06b"
            },
            "http://security.ubuntu.com/ubuntu/pool/main/o/openslp/libslp1_1.0.11-7ubuntu0.1_powerpc.deb": {
              "size": 48928,
              "md5": "ca8dfeddadab73241b9a3f36c6989e0d"
            }
          }
        },
        "i386": {
          "urls": {
            "http://security.ubuntu.com/ubuntu/pool/universe/o/openslp/slptool_1.0.11-7ubuntu0.1_i386.deb": {
              "size": 26086,
              "md5": "d83af46fc9e6e9981a6e5c5a1d23fdad"
            },
            "http://security.ubuntu.com/ubuntu/pool/universe/o/openslp/slpd_1.0.11-7ubuntu0.1_i386.deb": {
              "size": 65100,
              "md5": "ec67710b0585c62c7142f036256c9853"
            },
            "http://security.ubuntu.com/ubuntu/pool/main/o/openslp/libslp-dev_1.0.11-7ubuntu0.1_i386.deb": {
              "size": 62000,
              "md5": "fd04134fb0f1f98c2662d35ff340041d"
            },
            "http://security.ubuntu.com/ubuntu/pool/main/o/openslp/libslp1_1.0.11-7ubuntu0.1_i386.deb": {
              "size": 45890,
              "md5": "d703c3f516e7e67d918579f20c8c45aa"
            }
          }
        },
        "amd64": {
          "urls": {
            "http://security.ubuntu.com/ubuntu/pool/main/o/openslp/libslp1_1.0.11-7ubuntu0.1_amd64.deb": {
              "size": 47610,
              "md5": "a536d6a50a6d64453606178ec4f17ef1"
            },
            "http://security.ubuntu.com/ubuntu/pool/universe/o/openslp/slptool_1.0.11-7ubuntu0.1_amd64.deb": {
              "size": 26546,
              "md5": "44d2d312536407a1c2af16b265d04035"
            },
            "http://security.ubuntu.com/ubuntu/pool/universe/o/openslp/slpd_1.0.11-7ubuntu0.1_amd64.deb": {
              "size": 70866,
              "md5": "7f52d0fd37f71aec8e1940e1e34a9b63"
            },
            "http://security.ubuntu.com/ubuntu/pool/main/o/openslp/libslp-dev_1.0.11-7ubuntu0.1_amd64.deb": {
              "size": 65082,
              "md5": "9a8acfb6e05f13688bb9d54c85c3593b"
            }
          }
        }
      }
    }
  },
  "title": "OpenSLP vulnerabilities",
  "timestamp": 1111114024,
  "summary": "openslp vulnerabilities",
  "id": "USN-98-1",
  "cves": [
    "http://lists.grok.org.uk/pipermail/full-disclosure/2005-March/032534.html"
  ]
}
